MANIFEST.in
setup.py
ovos_ww_plugin_nyumaya/__init__.py
ovos_ww_plugin_nyumaya/libnyumaya.py
ovos_ww_plugin_nyumaya/multi_detector.py
ovos_ww_plugin_nyumaya/record.py
ovos_ww_plugin_nyumaya/ringbuffer.py
ovos_ww_plugin_nyumaya.egg-info/PKG-INFO
ovos_ww_plugin_nyumaya.egg-info/SOURCES.txt
ovos_ww_plugin_nyumaya.egg-info/dependency_links.txt
ovos_ww_plugin_nyumaya.egg-info/entry_points.txt
ovos_ww_plugin_nyumaya.egg-info/requires.txt
ovos_ww_plugin_nyumaya.egg-info/top_level.txt
ovos_ww_plugin_nyumaya.egg-info/zip-safe
ovos_ww_plugin_nyumaya/__pycache__/__init__.cpython-39.pyc
ovos_ww_plugin_nyumaya/__pycache__/libnyumaya.cpython-39.pyc
ovos_ww_plugin_nyumaya/lib/armv6/libnyumaya_premium.so
ovos_ww_plugin_nyumaya/lib/armv6/libnyumaya_premium.so.1.0.0
ovos_ww_plugin_nyumaya/lib/armv7/libnyumaya_premium.so
ovos_ww_plugin_nyumaya/lib/armv7/libnyumaya_premium.so.1.0.0
ovos_ww_plugin_nyumaya/lib/armv8/libnyumaya_premium.so
ovos_ww_plugin_nyumaya/lib/armv8/libnyumaya_premium.so.1.0.0
ovos_ww_plugin_nyumaya/lib/linux_x86_64/libnyumaya_premium.so
ovos_ww_plugin_nyumaya/lib/linux_x86_64/libnyumaya_premium.so.1.0.0
ovos_ww_plugin_nyumaya/models/commands/light_command.premium
ovos_ww_plugin_nyumaya/models/commands/off_command.premium
ovos_ww_plugin_nyumaya/models/commands/on_command.premium
ovos_ww_plugin_nyumaya/models/commands/stop_command.premium
ovos_ww_plugin_nyumaya/models/hotwords/alexa_v1.0.0.premium
ovos_ww_plugin_nyumaya/models/hotwords/firefox_v1.0.0.premium
ovos_ww_plugin_nyumaya/models/hotwords/marvin_v1.0.0.premium
ovos_ww_plugin_nyumaya/models/hotwords/sheila_v1.0.0.premium